Metadata-Version: 2.4
Name: xeno
Version: 7.10.0
Summary: The Python IOC app and build framework from outer space.
Home-page: https://github.com/lainproliant/xeno
Author: Lain Musgrove (lainproliant)
Author-email: lainproliant@gmail.com
License: BSD
Keywords: IOC dependency injector build system
Classifier: Development Status :: 5 - Production/Stable
Classifier: Intended Audience :: Developers
Classifier: Topic :: Software Development :: Libraries :: Application Frameworks
Classifier: License :: OSI Approved :: BSD License
Classifier: Programming Language :: Python :: 3.10
Classifier: Programming Language :: Python :: 3.11
License-File: LICENSE
Dynamic: author
Dynamic: author-email
Dynamic: classifier
Dynamic: description
Dynamic: description-content-type
Dynamic: home-page
Dynamic: keywords
Dynamic: license
Dynamic: license-file
Dynamic: summary
